jaxwell/__init__.py
jaxwell/cocg.py
jaxwell/fdfd.py
jaxwell/operators.py
jaxwell/utils.py
jaxwell/vecfield.py
jaxwell/tests/__init__.py
jaxwell/tests/test_cocg.py
jaxwell/tests/test_fdfd.py
jaxwell/tests/test_operators.py
jaxwell/tests/test_vecfield.py
jaxwell-0.2.0.dist-info/LICENSE
jaxwell-0.2.0.dist-info/WHEEL
jaxwell-0.2.0.dist-info/METADATA
jaxwell-0.2.0.dist-info/RECORD
