Metadata-Version: 2.1
Name: jaxwell
Version: 0.2.0
Summary: Jaxwell is JAX + Maxwell: an iterative solver for solving the finite-difference frequency-domain Maxwell equations on NVIDIA GPUs
Keywords: python
Author-email: Jesse Lu <mr.jesselu@gmail.com>, Jan David Fischbach <mail@jan-dav.id>
Requires-Python: >=3.6
Classifier: Programming Language :: Python :: 3.6
Classifier: Programming Language :: Python :: 3.7
Classifier: Programming Language :: Python :: 3.8
Classifier: Programming Language :: Python :: 3.9
Classifier: Programming Language :: Python :: 3.10
Classifier: Programming Language :: Python :: 3.11
Classifier: Operating System :: OS Independent
Classifier: License :: OSI Approved :: GNU General Public License v3 (GPLv3)
Requires-Dist: autograd
Requires-Dist: jax>=0.2.4
Requires-Dist: jaxlib>=0.2.4
Requires-Dist: numpy>=1.18.5
Requires-Dist: parameterized
Requires-Dist: pre-commit ; extra == "dev"
Requires-Dist: bumpversion ; extra == "dev"
Requires-Dist: jaxwell[tests] ; extra == "dev"
Requires-Dist: matplotlib ; extra == "docs"
Requires-Dist: jupyter-book==0.15.1 ; extra == "docs"
Requires-Dist: sphinx-autodoc-typehints ; extra == "docs"
Requires-Dist: sphinx-click ; extra == "docs"
Requires-Dist: pytest ; extra == "tests"
Requires-Dist: pytest-cov ; extra == "tests"
Requires-Dist: pytest-xdist ; extra == "tests"
Provides-Extra: dev
Provides-Extra: docs
Provides-Extra: tests
